docs/source/conf.py
lunae/__init__.py
lunae/__main__.py
lunae/py.typed
lunae/interpreter/__init__.py
lunae/interpreter/environment.py
lunae/language/syntax.py
lunae/language/typesystem.py
lunae/language/ast/base/block.py
lunae/language/ast/base/expr.py
lunae/language/ast/controls/forexpr.py
lunae/language/ast/controls/ifexpr.py
lunae/language/ast/controls/whileexpr.py
lunae/language/ast/functions/funccall.py
lunae/language/ast/functions/funcdef.py
lunae/language/ast/values/assign.py
lunae/language/ast/values/number.py
lunae/language/ast/values/string.py
lunae/language/ast/values/var.py
lunae/parser/__init__.py
lunae/parser/reader.py
lunae/parser/parsers/base/block.py
lunae/parser/parsers/base/expr.py
lunae/parser/parsers/base/primary.py
lunae/parser/parsers/base/statement.py
lunae/parser/parsers/controls/__init__.py
lunae/parser/parsers/controls/forexpr.py
lunae/parser/parsers/controls/ifexpr.py
lunae/parser/parsers/controls/whileexpr.py
lunae/parser/parsers/functions/funccall.py
lunae/parser/parsers/functions/funcdef.py
lunae/parser/parsers/operations/binary.py
lunae/parser/parsers/operations/unary.py
lunae/parser/parsers/values/assign.py
lunae/parser/parsers/values/number.py
lunae/parser/parsers/values/string.py
lunae/parser/parsers/values/var.py
lunae/repl/__init__.py
lunae/tokenizer/__init__.py
lunae/tokenizer/grammar.py
lunae/tokenizer/reader.py
lunae/tokenizer/token.py
lunae/utils/errors.py
lunae/utils/indent.py
lunae/utils/sourceposition.py
lunae-0.0.6.dist-info/licenses/LICENSE
tests/test_base.py
tests/test_typesystem.py
lunae-0.0.6.dist-info/METADATA
lunae-0.0.6.dist-info/WHEEL
lunae-0.0.6.dist-info/entry_points.txt
lunae-0.0.6.dist-info/top_level.txt
lunae-0.0.6.dist-info/RECORD
