Metadata-Version: 2.4
Name: lunae
Version: 0.0.6
Summary: Lunae is a lightweight programming language designed for simplicity and extensibility.
Author-email: Etienne_MR <etienne@etiennemr.fr>
License-Expression: MIT
Project-URL: Homepage, https://github.com/EtienneMR/lunae
Classifier: Programming Language :: Python :: 3
Classifier: Operating System :: OS Independent
Requires-Python: >=3.8
License-File: LICENSE
Dynamic: license-file
